pep543/__init__.py
pep543-0.0.1.dist-info/DESCRIPTION.rst
pep543-0.0.1.dist-info/METADATA
pep543-0.0.1.dist-info/RECORD
pep543-0.0.1.dist-info/WHEEL
pep543-0.0.1.dist-info/metadata.json
pep543-0.0.1.dist-info/top_level.txt
